loopia_of_fury/__init__.py
loopia_of_fury/__main__.py
loopia_of_fury-1.3.0.dist-info/METADATA
loopia_of_fury-1.3.0.dist-info/WHEEL
loopia_of_fury-1.3.0.dist-info/entry_points.txt
loopia_of_fury-1.3.0.dist-info/RECORD
